joto_api/__init__.py
joto_api-0.1.3.dist-info/LICENSE
joto_api-0.1.3.dist-info/METADATA
joto_api-0.1.3.dist-info/WHEEL
joto_api-0.1.3.dist-info/top_level.txt
joto_api-0.1.3.dist-info/RECORD
